topsis/__init__.py
topsis/topsis.py
Topsis_Samkit_102203285-1.0.0.dist-info/LICENSE
Topsis_Samkit_102203285-1.0.0.dist-info/METADATA
Topsis_Samkit_102203285-1.0.0.dist-info/WHEEL
Topsis_Samkit_102203285-1.0.0.dist-info/top_level.txt
Topsis_Samkit_102203285-1.0.0.dist-info/RECORD
