Metadata-Version: 2.1
Name: Topsis-Samkit-102203285
Version: 1.0.0
Summary: A Python package for performing TOPSIS analysis.
Home-page: https://github.com/gatopotato/Topsis-Samkit-102203285
Author: Samkit Jaina
Author-email: samkitjaina.ind@gmail.com
Classifier: Programming Language :: Python :: 3
Classifier: License :: OSI Approved :: MIT License
Classifier: Operating System :: OS Independent
Requires-Python: >=3.6
License-File: LICENSE
Requires-Dist: pandas
Requires-Dist: numpy
Requires-Dist: openpyxl
